django_grappelli_custom_autocomplete/__init__.py
django_grappelli_custom_autocomplete/admin.py
django_grappelli_custom_autocomplete/urls.py
django_grappelli_custom_autocomplete/static/django_grappelli_custom_autocomplete/css/django-grappelli-custom-autocomplete.css
django_grappelli_custom_autocomplete/static/django_grappelli_custom_autocomplete/images/icons-s846f870921.png
django_grappelli_custom_autocomplete/static/django_grappelli_custom_autocomplete/js/grp_custom_autocomplete_functions.js
django_grappelli_custom_autocomplete/static/django_grappelli_custom_autocomplete/js/jquery.grp_custom_autocomplete_fk.js
django_grappelli_custom_autocomplete/static/django_grappelli_custom_autocomplete/js/jquery.grp_custom_autocomplete_generic.js
django_grappelli_custom_autocomplete/static/django_grappelli_custom_autocomplete/js/jquery.grp_custom_autocomplete_m2m.js
django_grappelli_custom_autocomplete/templates/admin/django_grappelli_custom_autocomplete/change_form.html
django_grappelli_custom_autocomplete/templates/admin/django_grappelli_custom_autocomplete/edit_inline/stacked.html
django_grappelli_custom_autocomplete/templates/admin/django_grappelli_custom_autocomplete/edit_inline/tabular.html
django_grappelli_custom_autocomplete/templatetags/__init__.py
django_grappelli_custom_autocomplete/templatetags/custom_autocomplete_tags.py
django_grappelli_custom_autocomplete/views/__init__.py
django_grappelli_custom_autocomplete/views/related.py
django_grappelli_custom_autocomplete-1.4.1.dist-info/DESCRIPTION.rst
django_grappelli_custom_autocomplete-1.4.1.dist-info/METADATA
django_grappelli_custom_autocomplete-1.4.1.dist-info/RECORD
django_grappelli_custom_autocomplete-1.4.1.dist-info/WHEEL
django_grappelli_custom_autocomplete-1.4.1.dist-info/metadata.json
django_grappelli_custom_autocomplete-1.4.1.dist-info/top_level.txt
