Metadata-Version: 2.0
Name: django-grappelli-custom-autocomplete
Version: 1.4.1
Summary: Customize the template for autocomplete lookups.
Home-page: https://github.com/ninapavlich/django-grappelli-custom-autocomplete
Author: Nina Pavlich
Author-email: nina@ninalp.com
License: BSD
Platform: UNKNOWN
Classifier: Development Status :: 4 - Beta
Classifier: Environment :: Web Environment
Classifier: Framework :: Django
Classifier: Intended Audience :: Developers
Classifier: License :: OSI Approved
Classifier: Operating System :: OS Independent
Classifier: Programming Language :: Python
